reg_normalizer/__init__.py
reg_normalizer/constants.py
reg_normalizer/regions_validator.py
reg_normalizer/data/interim/regions_etalon_v2.0.yaml
reg_normalizer-1.0.11.dist-info/METADATA
reg_normalizer-1.0.11.dist-info/WHEEL
reg_normalizer-1.0.11.dist-info/top_level.txt
reg_normalizer-1.0.11.dist-info/RECORD
