Metadata-Version: 2.4
Name: reg-normalizer
Version: 1.0.11
Summary: Tool for normalizing and standardizing Russian region names
Author-email: Vitovt Kopytok <vitovt.kopytok@gmail.com>
License: CC BY-NC-SA 4.0
Project-URL: Homepage, https://github.com/tochno-st/reg_normalizer
Project-URL: Documentation, https://github.com/tochno-st/reg_normalizer#readme
Project-URL: Repository, https://github.com/tochno-st/reg_normalizer
Project-URL: Bug Tracker, https://github.com/tochno-st/reg_normalizer/issues
Keywords: regions,normalization,russian,fuzzy-matching,data-cleaning
Classifier: Development Status :: 4 - Beta
Classifier: Intended Audience :: Developers
Classifier: Intended Audience :: Science/Research
Classifier: License :: Free for non-commercial use
Classifier: Programming Language :: Python :: 3
Classifier: Programming Language :: Python :: 3.8
Classifier: Programming Language :: Python :: 3.9
Classifier: Programming Language :: Python :: 3.10
Classifier: Programming Language :: Python :: 3.11
Classifier: Programming Language :: Python :: 3.12
Classifier: Operating System :: OS Independent
Classifier: Topic :: Software Development :: Libraries :: Python Modules
Classifier: Topic :: Text Processing :: Linguistic
Classifier: Natural Language :: Russian
Requires-Python: >=3.8
Requires-Dist: pyyaml>=6.0
Requires-Dist: fuzzywuzzy>=0.18.0
Requires-Dist: python-levenshtein>=0.20.0
Requires-Dist: pandas>=1.5.0
Requires-Dist: nltk>=3.8.0
Provides-Extra: dev
Requires-Dist: ipykernel; extra == "dev"
Requires-Dist: pytest>=7.0; extra == "dev"
Requires-Dist: pytest-cov; extra == "dev"
